ngxctl/__init__.py
ngxctl/cli.py
ngxctl/cmds/__init__.py
ngxctl/cmds/extractor.py
ngxctl/cmds/top.py
ngxctl/utils/__init__.py
ngxctl/utils/config_parser.py
ngxctl/utils/file_reader.py
ngxctl/utils/file_watcher.py
ngxctl/utils/misc_utils.py
ngxctl/utils/sqlite_utils.py
ngxctl/utils/top_stat.py
scripts/__init__.py
scripts/extract_variable_from_log_format.py
scripts/file_reader_demo.py
scripts/tabulate_display.py
tests/__init__.py
tests/test_sqlite_utils.py
tests/test_top.py
ngxctl-0.1.0.dist-info/LICENSE
ngxctl-0.1.0.dist-info/METADATA
ngxctl-0.1.0.dist-info/WHEEL
ngxctl-0.1.0.dist-info/entry_points.txt
ngxctl-0.1.0.dist-info/top_level.txt
ngxctl-0.1.0.dist-info/RECORD
