Metadata-Version: 2.1
Name: ngxctl
Version: 0.1.0
Summary: A command-line tool for managing and analyzing Nginx.
Author: RangerWolf
Author-email: rangerwolf@gmail.com
Classifier: Programming Language :: Python :: 3
Classifier: License :: OSI Approved :: MIT License
Classifier: Operating System :: OS Independent
Requires-Python: >=3.6
License-File: LICENSE
Requires-Dist: crossplane==0.5.8
Requires-Dist: pandas==2.0.3
Requires-Dist: jsonpath-ng==1.6.1
Requires-Dist: tabulate==0.9.0
Requires-Dist: click==8.1.7
